action_hero/__init__.py
action_hero/email.py
action_hero/email_utils.py
action_hero/getters.py
action_hero/misc.py
action_hero/net.py
action_hero/net_utils.py
action_hero/path.py
action_hero/path_utils.py
action_hero/range.py
action_hero/types.py
action_hero/types_utils.py
action_hero/utils.py
meta/__init__.py
meta/about.ini
action_hero-0.7.0.dist-info/LICENSE
action_hero-0.7.0.dist-info/METADATA
action_hero-0.7.0.dist-info/WHEEL
action_hero-0.7.0.dist-info/top_level.txt
action_hero-0.7.0.dist-info/RECORD
