Metadata-Version: 2.1
Name: action-hero
Version: 0.7.0
Summary: Make powerful CLIs with argparse actions that pack a punch! 
Home-page: https://github.com/kadimisetty/action-hero
Author: Sri Kadimisetty
Author-email: s@sri.io
License: MIT
Platform: UNKNOWN
Classifier: Intended Audience :: Developers
Classifier: License :: OSI Approved :: MIT License
Classifier: Programming Language :: Python :: 3.5
Classifier: Programming Language :: Python :: 3.6
Classifier: Programming Language :: Python :: 3.7
Classifier: Programming Language :: Python :: 3.8
Classifier: Programming Language :: Python :: Implementation :: CPython
Classifier: Programming Language :: Python :: Implementation :: PyPy
Classifier: Topic :: Software Development :: Libraries :: Python Modules
Classifier: Topic :: Software Development :: Libraries
Classifier: Topic :: Terminals
Classifier: Natural Language :: English
Requires-Python: >=3.5.0
Requires-Dist: requests
Requires-Dist: pyyaml
